{
    "data": [
        {
            "id": "bg",
            "src": "bg2",
            "ext": "png",
            "cw": 927,
            "ch": 428
        },
        {
            "id": "piggybank",
            "src": "piggybank",
            "ext": "png",
            "cw": 513,
            "ch": 362
        },
        {
            "id": "piggybankbroke",
            "src": "piggybankbroke",
            "ext": "png",
            "cw": 513,
            "ch": 362
        },
        {
            "id": "pigscore",
            "src": "pigscore",
            "ext": "png",
            "cw": 128,
            "ch": 104
        },
        {
            "id": "shine",
            "src": "shine",
            "ext": "png",
            "cw": 352,
            "ch": 290
        },
        {
            "id": "life",
            "src": "life",
            "ext": "png",
            "cw": 48,
            "ch": 48
        },
        {
            "id": "money",
            "src": "money",
            "ext": "png",
            "cw": 113,
            "ch": 113
        },
        {
            "id": "stopwatch",
            "src": "hud/stopwatch",
            "ext": "png",
            "cw": 43,
            "ch": 45
        },
        {
            "id": "timecircle",
            "src": "hud/timecircle",
            "ext": "png",
            "cw": 45,
            "ch": 45
        },
        {
            "id": "coin_0",
            "src": "coins/coin_0",
            "ext": "png",
            "cw": 39,
            "ch": 41
        },
        {
            "id": "coin_1",
            "src": "coins/coin_1",
            "ext": "png",
            "cw": 82,
            "ch": 82
        },
        {
            "id": "coin_2",
            "src": "coins/coin_2",
            "ext": "png",
            "cw": 82,
            "ch": 82
        },
        {
            "id": "coin_3",
            "src": "coins/coin_3",
            "ext": "png",
            "cw": 82,
            "ch": 82
        },
        {
            "id": "glue",
            "src": "glue",
            "ext": "png",
            "cw": 1103,
            "ch": 1102
        },
        {
            "id": "hammer",
            "src": "hammer2",
            "ext": "png",
            "cw": 1887,
            "ch": 3764
        },
        {
            "id": "kaboom",
            "src": "kaboom",
            "ext": "png",
            "cw": 108,
            "ch": 28
        },
        {
            "id": "kaboomstar",
            "src": "kaboomstar",
            "ext": "png",
            "cw": 175,
            "ch": 152
        },
        {
            "id": "ball_1",
            "src": "balls/1",
            "ext": "png",
            "cw": 293,
            "ch": 293
        },
        {
            "id": "ball_2",
            "src": "balls/2",
            "ext": "png",
            "cw": 293,
            "ch": 293
        },
        {
            "id": "ball_3",
            "src": "balls/3",
            "ext": "png",
            "cw": 293,
            "ch": 293
        },
        {
            "id": "ball_4",
            "src": "balls/4",
            "ext": "png",
            "cw": 293,
            "ch": 293
        },
        {
            "id": "ball_5",
            "src": "balls/5",
            "ext": "png",
            "cw": 293,
            "ch": 293
        },
        {
            "id": "startrect",
            "src": "startrect",
            "ext": "png",
            "cw": 927,
            "ch": 429
        },
        {
            "id": "title",
            "src": "title",
            "ext": "png",
            "cw": 255,
            "ch": 89
        },
        {
            "id": "text1",
            "src": "text1",
            "ext": "png",
            "cw": 108,
            "ch": 29
        },
        {
            "id": "text2",
            "src": "text2",
            "ext": "png",
            "cw": 124,
            "ch": 25
        },
        {
            "id": "text3",
            "src": "text3",
            "ext": "png",
            "cw": 121,
            "ch": 27
        },
        {
            "id": "text4",
            "src": "text4",
            "ext": "png",
            "cw": 127,
            "ch": 40
        },
        {
            "id": "hand",
            "src": "hand",
            "ext": "png",
            "cw": 57,
            "ch": 57
        },
        {
            "id": "startcoin",
            "src": "startcoin",
            "ext": "png",
            "cw": 57,
            "ch": 57
        },
        {
            "id": "starthammer",
            "src": "starthammer",
            "ext": "png",
            "cw": 80,
            "ch": 80
        },
        {
            "id": "startball",
            "src": "startball",
            "ext": "png",
            "cw": 45,
            "ch": 45
        },
        {
            "id": "startpig",
            "src": "startpig",
            "ext": "png",
            "cw": 67,
            "ch": 57
        },
        {
            "id": "beginbutton",
            "src": "beginbutton",
            "ext": "png",
            "cw": 213,
            "ch": 49
        },
        {
            "id": "volume",
            "src": "volume",
            "ext": "png",
            "cw": 50,
            "ch": 50
        },
        {
            "id": "mute",
            "src": "mute",
            "ext": "png",
            "cw": 50,
            "ch": 50
        }
    ]
}
